fastmsc/__init__.py
fastmsc/_modidx.py
fastmsc/core.py
fastmsc/utils.py
fastmsc-0.0.2.dist-info/LICENSE
fastmsc-0.0.2.dist-info/METADATA
fastmsc-0.0.2.dist-info/WHEEL
fastmsc-0.0.2.dist-info/entry_points.txt
fastmsc-0.0.2.dist-info/top_level.txt
fastmsc-0.0.2.dist-info/RECORD
