Metadata-Version: 2.1
Name: fastmsc
Version: 0.0.2
Summary: Utilities for thesis
Home-page: https://github.com/bdsaglam/fastmsc
Author: Barış Deniz Sağlam
Author-email: bdsaglam@gmail.com
License: Apache Software License 2.0
Keywords: nbdev jupyter notebook python
Classifier: Development Status :: 4 - Beta
Classifier: Intended Audience :: Developers
Classifier: Natural Language :: English
Classifier: Programming Language :: Python :: 3.7
Classifier: Programming Language :: Python :: 3.8
Classifier: Programming Language :: Python :: 3.9
Classifier: Programming Language :: Python :: 3.10
Classifier: License :: OSI Approved :: Apache Software License
Requires-Python: >=3.7
License-File: LICENSE
Requires-Dist: numpy
Requires-Dist: pandas
Requires-Dist: fastcore
Requires-Dist: fastai
Provides-Extra: dev
Requires-Dist: twine ; extra == 'dev'
